Workbook

Sheet 使い方
A1: 電力小売データ分析基盤 ヒアリングシート兼適合分析表
A3: 文書名 | B3: ヒアリングシート兼適合分析表（Excel 版・記入用）
A4: 版 | B4: 1.0（正式版）
A5: 工程 | B5: 03 要件定義（ヒアリングと適合分析）
A6: 入力 | B6: 機能一覧（02_製品機能/機能一覧.xlsx）、知識体系
A7: 作成・承認 | B7: ヒアリングと判定：コンサルタント／GAP の影響範囲と改修提案：SE／対策の採否：管理者（投資を伴うものは経営者）／全体の承認：PM
A8: 記入する欄 | B8: 「ヒアリング」シートの黄色の列（回答〜状態）だけに記入する。青い見出しの列（項目ID〜GAP 時の対策の考え方）は標準機能の定義なので変更しない
A9: 集計 | B9: 「集計」シートは記入内容から自動で計算される（数式）
A11: 進め方
A12: 1. 準備 | B12: 機能一覧と本シートを導入先へ事前に送り、回答者（部署）を割り当てる（PM・コンサルタント）
A13: 2. ヒアリング | B13: 機能ごとに「標準機能の内容」を説明し、「確認事項」を質問して「回答」に記入する（コンサルタント／回答：業務担当者）
A14: 3. 判定 | B14: 回答をもとに「判定」を選ぶ（コンサルタント）
A15: 4. GAP 分析 | B15: 判定が GAP の項目に「GAP の内容」「影響範囲」「影響する工程」「対策区分」「改修提案」「影響度」を記入する（SE）
A16: 5. 対策の決定 | B16: 「決定内容」「根拠資料」「決定者氏名」「決定日」を記入し、「状態」を「決定済み」にする（管理者。投資を伴うものは経営者）
A17: 6. 完了 | B17: 集計シートの「未決定」が 0 になったら要件定義を完了する（PM）
A19: 選択肢の意味
A20: 判定 | B20: 適合＝標準機能のまま使える／条件付き適合＝設定（マスタ・パラメータの登録）で吸収できる／GAP＝改修または運用での回避が必要／対象外＝導入先の業務に該当しない
A21: 対策区分 | B21: 設定＝パラメータ・区分値の登録／マスタ追加＝マスタの行・区分の追加／ロジック改修＝計算・判定・データ構造の変更（基本設計〜運用のすべてに影響）／運用で回避＝業務手順で吸収
A22: 影響度 | B22: 大＝複数機能・データ構造に及ぶ、または過去データの再計算が必要／中＝1機能内の計算・判定の変更／小＝設定・マスタ登録で済む
A23: 影響範囲 | B23: 影響する機能ID と、影響するデータ（機能一覧の「主なデータ」の論理名）を書く。設計書の各章は機能ID を持つため、機能ID から影響する設計箇所を特定できる
A24: 状態 | B24: 未着手／確認中／回答済み／決定済み
A26: 記入例（F08-01 で GAP となった場合）
A27: 回答 | B27: 固定単価メニューの高圧需要家のうち12社に、基本料金の個別値引き（3〜5%）がある
A28: 判定 | B28: GAP
A29: GAP の内容 | B29: 固定単価メニューの需要家別値引きを標準の構造で表せない
A30: 影響範囲（機能ID・データ） | B30: F-08 小売売上計算／料金メニューマスタ、日報損益マート（売上）
A31: 影響する工程 | B31: 基本設計・詳細設計・ソースコード・導入
A32: 対策区分 | B32: ロジック改修
A33: 改修提案 | B33: 料金メニューの単価に需要家単位の上書き行を追加し、日報バッチの単価解決で優先適用する。代替案：顧客専用のメニューコードを12個登録する（マスタ追加で済むが、メニュー数が増える）
A34: 影響度 | B34: 中
A35: 決定内容 | B35: 代替案（顧客専用メニューコード）を採用。値引き先が20社を超えた時点で改修を再検討する
A36: 根拠資料 | B36: 料金メニュー表（2026年4月版）、営業部の特約一覧
A37: 決定者氏名 | B37: 料金部長 山田
A38: 決定日 | B38: 2026/10/05
... A40: 状態 | B40: 決定済み

Sheet ヒアリング
A1: 項目ID | B1: 機能ID | C1: 機能 | D1: 区分 | E1: 確認事項 | F1: 標準機能の内容 | G1: 回答者（役割） | H1: 決定者（役割） | I1: 未確定のまま進めた場合の影響 | J1: GAP 時の対策の考え方 | K1: 回答 | L1: 回答者氏名 | M1: 回答日 | N1: 判定 | O1: GAP の内容 | P1: 影響範囲（機能ID・データ） | Q1: 影響する工程 | R1: 対策区分 | S1: 改修提案 | T1: 影響度 | U1: 決定内容 | V1: 根拠資料 | W1: 決定者氏名 | X1: 決定日 | Y1: 期限 | Z1: 状態
A2: F01-01 | B2: F-01 | C2: 基盤マスタ・取引先管理 | D2: 制度確認 | E2: 事業者コード3種（登録番号、エリアごとの小売事業者コード5桁、一般送配電事業者コード）をどの資料から取得するか。 | F2: 登録番号は資源エネルギー庁の登録小売電気事業者一覧から一括投入する。小売事業者コードは一括提供がないため、OCCTO スイッチング支援システム・供給計画届出書・JEPX 取引明細のいずれかから進出エリア分を抽出する。一般送配電事業者コードは各一送の EDI 仕様書の巻末マスタ、または受信済みの託送請求データ・確報データのファイルヘッダーから取得する。 | G2: 業務担当者（需給管理部・情報システム部） | H2: 管理者 | I2: 外部データの名寄せができず、取込が停止する。 | J2: マスタ追加（取得元が異なるだけであれば登録手順の変更で吸収） | Z2: 未着手
A3: F01-02 | B3: F-01 | C3: 基盤マスタ・取引先管理 | D3: 機能確認 | E3: 事業エリアはどこか。沖縄エリアでの事業はあるか。 | F3: 北海道〜九州の9エリアを対象とする。沖縄は対象外。 | G3: 業務担当者（経営企画・需給管理部） | H3: 経営者 | I3: 対象外エリアのデータが取り込まれ、入口で拒否される。 | J3: ロジック改修（沖縄を対象にする場合は、インバランス制度の違いを含む大規模な改修） | Z3: 未着手
A4: F01-03 | B4: F-01 | C4: 基盤マスタ・取引先管理 | D4: 機能確認 | E4: 同じ取引先が需要家と電源の供給者を兼ねるケースはあるか。BG に参加している取引先はどれか。 | F4: 取引先は1つのマスタで管理し、需要家・供給者・BG構成員の役割をフラグで持つ。1社が複数の役割を持てる。 | G4: 業務担当者（営業部・電源開発部） | H4: 管理者 | I4: 取引先の重複登録により、取引先単位の集計が分かれる。 | J4: 設定（役割フラグの登録） | Z4: 未着手
A5: F02-01 | B5: F-02 | C5: 需要家・契約管理 | D5: 業務決定 | E5: 個人需要家の取引先IDの採番規則をどうするか。取引先名に氏名を入れない運用を徹底できるか。 | F5: 個人需要家は「IND_＋需要家ID」で採番し、取引先名は固定ラベル「個人需要家」とする。氏名は需要家マスタの個人情報の列にのみ持つ。 | G5: 業務担当者（営業部・情報システム部） | H5: 管理者 | I5: 取引先マスタに個人情報が流入し、閲覧制限の付与範囲が参照元へ連鎖して制御できなくなる。 | J5: 運用で回避（採番規則の変更は設定で吸収） | Z5: 未着手
A6: F02-02 | B6: F-02 | C6: 需要家・契約管理 | D6: 機能確認 | E6: 既存システムの契約履歴に、期間の重複（同じ日に複数プランが有効）や隙間（未契約の期間）はどの程度あるか。 | F6: 契約履歴は期間管理とし、重複・隙間・開始終了の逆転を検証で拒否する。 | G6: 業務担当者（料金担当） | H6: 管理者 | I6: 移行が長期化し、日報で単価が引けない日が発生する。 | J6: 運用で回避（移行前に業務側で是正する） | Z6: 未着手
A7: F02-03 | B7: F-02 | C7: 需要家・契約管理 | D7: 機能確認 | E7: 供給地点特定番号をどの経路で登録しているか（画面・API・一括取込）。 | F7: 全入口で先頭3桁（エリア2桁＋電圧区分1桁）を検証し、不一致は登録を拒否する。初回取込時に一送の検針データとの突合で実在も確認する。 | G7: 業務担当者（営業部・情報システム部） | H7: 管理者 | I7: 誤った地点番号が実績取込の失敗として後から発覚する。 | J7: 設定（検証の入口を追加する場合はロジック改修） | Z7: 未着手
A8: F02-04 | B8: F-02 | C8: 需要家・契約管理 | D8: 機能確認 | E8: 特定の需要家に専属させる相対契約・コーポレートPPA はあるか。 | F8: 需要家契約に専属調達契約を指定でき、指定された契約はその需要家にだけ配分する。指定のない契約はエリア全体で按分する。 | G8: 業務担当者（需給管理部・営業部） | H8: 管理者 | I8: 専属契約の原価がエリア全体に配分され、需要家別の粗利がずれる。 | J8: 設定 | Z8: 未着手
A9: F03-01 | B9: F-03 | C9: 単価・制度マスタ管理 | D9: 制度確認 | E9: エリア別・電圧別の送電損失率の具体値と適用式（除すか乗じるか）は、各一送の最新の託送供給等約款（別表）と一致しているか。 | F9: 受電端電力量 ÷ (1 − 送電損失率) で送電端に換算する。損失率は期間管理で登録する。 | G9: 業務担当者（需給管理部） | H9: 管理者 | I9: 初期マスタが確定せず、過去データでの検算が進められない。 | J9: マスタ追加（換算式が異なる場合は損失補正の1箇所のみロジック改修） | Z9: 未着手
A10: F03-02 | B10: F-03 | C10: 単価・制度マスタ管理 | D10: 制度確認 | E10: 託送料金・発電側課金の単価と割引区分の判定条件は何か。季節・休日・時間帯の区分、冬季の特掲の有無、休日昼間の適用単価はどうなっているか。 | F10: 託送料金は一律従量と季節別時間帯別を同じ構造で持ち、判定の優先順は「夜間＞休日＞夏季ピーク＞夏季昼間＞冬季昼間＞標準」。時間帯別の単価が空欄なら標準単価を使う。 | G10: 業務担当者（需給管理部・料金担当） | H10: 管理者 | I10: 託送原価が約款と合わず、請求突合がずれる。 | J10: マスタ追加（休日ルール・季節境界の登録で吸収） | Z10: 未着手
A11: F03-03 | B11: F-03 | C11: 単価・制度マスタ管理 | D11: 制度確認 | E11: 容量拠出金は一律 kWh 按分でよいか。容量市場の精算仕様（ピーク時 kW 按分への移行、年度別単価の改定）に変更はないか。 | F11: 受電端電力量に対する一律 kWh 按分で原価計上する。ピーク時 kW 按分用の単価列は予備として持つ。制度の見直しは年次で確認する。 | G11: 業務担当者（需給管理部） | H11: 管理者 | I11: 容量拠出金の原価が制度と合わなくなる。 | J11: 設定（予備の単価列を有効化） | Z11: 未着手
A12: F03-04 | B12: F-03 | C12: 単価・制度マスタ管理 | D12: 制度確認 | E12: FIP バランシングコストの年度別単価（基本部分と激変緩和の上乗せ、上乗せの終了年度）は何か。 | F12: 認定年度 × 実需給年度 × 電源 × エリアの4軸で登録し、上乗せの終了年度以降は上乗せ 0 を明示的に登録する。 | G12: 業務担当者（電源開発部） | H12: 管理者 | I12: FIP の交付金収入が過大または過小に計上される。 | J12: マスタ追加 | Z12: 未着手
A13: F03-05 | B13: F-03 | C13: 単価・制度マスタ管理 | D13: 制度確認 | E13: 燃料費調整単価の公表元の税区分（税込・税抜）と上限の有無は何か。 | F13: 公表値のまま税区分付きで保持し、集計マート層で税抜化する（丸めない）。 | G13: 業務担当者（料金担当） | H13: 管理者 | I13: 燃調の売上が税区分の違いでずれる。 | J13: 設定（税区分列の登録） | Z13: 未着手
... A78: N06-01 | B78: N-06 | C78: 命名・開発規約 | D78: 非機能 | E78: 社内に既存の命名・開発規約があるか。外部の「データ基盤開発運用ガイドライン」への準拠でよいか。 | F78: 外部の「データ基盤開発運用ガイドライン」に準拠する。 | G78: SE（情報システム部） | H78: PM | I78: 既存資産との命名が不統一になる。 | J78: ロジック改修（命名変更は破壊的変更） | Z78: 未着手

Sheet 集計
A1: 機能別の判定と決定の状況（ヒアリングシートの記入内容から自動計算）
A3: 機能ID | B3: 機能 | C3: 項目数 | D3: 適合 | E3: 条件付き適合 | F3: GAP | G3: 対象外 | H3: 未判定 | I3: うち GAP の対策区分：ロジック改修 | J3: 決定済み | K3: 未決定
A4: F-01 | B4: 基盤マスタ・取引先管理 | C4: =COUNTIF(ヒアリング!$B$2:$B$78,A4) -> 3 | D4: =COUNTIFS(ヒアリング!$B$2:$B$78,$A4,ヒアリング!$N$2:$N$78,"適合") -> 0 | E4: =COUNTIFS(ヒアリング!$B$2:$B$78,$A4,ヒアリング!$N$2:$N$78,"条件付き適合") -> 0 | F4: =COUNTIFS(ヒアリング!$B$2:$B$78,$A4,ヒアリング!$N$2:$N$78,"GAP") -> 0 | G4: =COUNTIFS(ヒアリング!$B$2:$B$78,$A4,ヒアリング!$N$2:$N$78,"対象外") -> 0 | H4: =C4-SUM(D4:G4) -> 3 | I4: =COUNTIFS(ヒアリング!$B$2:$B$78,$A4,ヒアリング!$N$2:$N$78,"GAP",ヒアリング!$R$2:$R$78,"ロジック改修") -> 0 | J4: =COUNTIFS(ヒアリング!$B$2:$B$78,$A4,ヒアリング!$Z$2:$Z$78,"決定済み") -> 0 | K4: =C4-J4 -> 3
A5: F-02 | B5: 需要家・契約管理 | C5: =COUNTIF(ヒアリング!$B$2:$B$78,A5) -> 4 | D5: =COUNTIFS(ヒアリング!$B$2:$B$78,$A5,ヒアリング!$N$2:$N$78,"適合") -> 0 | E5: =COUNTIFS(ヒアリング!$B$2:$B$78,$A5,ヒアリング!$N$2:$N$78,"条件付き適合") -> 0 | F5: =COUNTIFS(ヒアリング!$B$2:$B$78,$A5,ヒアリング!$N$2:$N$78,"GAP") -> 0 | G5: =COUNTIFS(ヒアリング!$B$2:$B$78,$A5,ヒアリング!$N$2:$N$78,"対象外") -> 0 | H5: =C5-SUM(D5:G5) -> 4 | I5: =COUNTIFS(ヒアリング!$B$2:$B$78,$A5,ヒアリング!$N$2:$N$78,"GAP",ヒアリング!$R$2:$R$78,"ロジック改修") -> 0 | J5: =COUNTIFS(ヒアリング!$B$2:$B$78,$A5,ヒアリング!$Z$2:$Z$78,"決定済み") -> 0 | K5: =C5-J5 -> 4
A6: F-03 | B6: 単価・制度マスタ管理 | C6: =COUNTIF(ヒアリング!$B$2:$B$78,A6) -> 9 | D6: =COUNTIFS(ヒアリング!$B$2:$B$78,$A6,ヒアリング!$N$2:$N$78,"適合") -> 0 | E6: =COUNTIFS(ヒアリング!$B$2:$B$78,$A6,ヒアリング!$N$2:$N$78,"条件付き適合") -> 0 | F6: =COUNTIFS(ヒアリング!$B$2:$B$78,$A6,ヒアリング!$N$2:$N$78,"GAP") -> 0 | G6: =COUNTIFS(ヒアリング!$B$2:$B$78,$A6,ヒアリング!$N$2:$N$78,"対象外") -> 0 | H6: =C6-SUM(D6:G6) -> 9 | I6: =COUNTIFS(ヒアリング!$B$2:$B$78,$A6,ヒアリング!$N$2:$N$78,"GAP",ヒアリング!$R$2:$R$78,"ロジック改修") -> 0 | J6: =COUNTIFS(ヒアリング!$B$2:$B$78,$A6,ヒアリング!$Z$2:$Z$78,"決定済み") -> 0 | K6: =C6-J6 -> 9
A7: F-04 | B7: カレンダー・休日管理 | C7: =COUNTIF(ヒアリング!$B$2:$B$78,A7) -> 5 | D7: =COUNTIFS(ヒアリング!$B$2:$B$78,$A7,ヒアリング!$N$2:$N$78,"適合") -> 0 | E7: =COUNTIFS(ヒアリング!$B$2:$B$78,$A7,ヒアリング!$N$2:$N$78,"条件付き適合") -> 0 | F7: =COUNTIFS(ヒアリング!$B$2:$B$78,$A7,ヒアリング!$N$2:$N$78,"GAP") -> 0 | G7: =COUNTIFS(ヒアリング!$B$2:$B$78,$A7,ヒアリング!$N$2:$N$78,"対象外") -> 0 | H7: =C7-SUM(D7:G7) -> 5 | I7: =COUNTIFS(ヒアリング!$B$2:$B$78,$A7,ヒアリング!$N$2:$N$78,"GAP",ヒアリング!$R$2:$R$78,"ロジック改修") -> 0 | J7: =COUNTIFS(ヒアリング!$B$2:$B$78,$A7,ヒアリング!$Z$2:$Z$78,"決定済み") -> 0 | K7: =C7-J7 -> 5
A8: F-05 | B8: 市場・外部データ取込 | C8: =COUNTIF(ヒアリング!$B$2:$B$78,A8) -> 3 | D8: =COUNTIFS(ヒアリング!$B$2:$B$78,$A8,ヒアリング!$N$2:$N$78,"適合") -> 0 | E8: =COUNTIFS(ヒアリング!$B$2:$B$78,$A8,ヒアリング!$N$2:$N$78,"条件付き適合") -> 0 | F8: =COUNTIFS(ヒアリング!$B$2:$B$78,$A8,ヒアリング!$N$2:$N$78,"GAP") -> 0 | G8: =COUNTIFS(ヒアリング!$B$2:$B$78,$A8,ヒアリング!$N$2:$N$78,"対象外") -> 0 | H8: =C8-SUM(D8:G8) -> 3 | I8: =COUNTIFS(ヒアリング!$B$2:$B$78,$A8,ヒアリング!$N$2:$N$78,"GAP",ヒアリング!$R$2:$R$78,"ロジック改修") -> 0 | J8: =COUNTIFS(ヒアリング!$B$2:$B$78,$A8,ヒアリング!$Z$2:$Z$78,"決定済み") -> 0 | K8: =C8-J8 -> 3
A9: F-06 | B9: 計画管理 | C9: =COUNTIF(ヒアリング!$B$2:$B$78,A9) -> 2 | D9: =COUNTIFS(ヒアリング!$B$2:$B$78,$A9,ヒアリング!$N$2:$N$78,"適合") -> 0 | E9: =COUNTIFS(ヒアリング!$B$2:$B$78,$A9,ヒアリング!$N$2:$N$78,"条件付き適合") -> 0 | F9: =COUNTIFS(ヒアリング!$B$2:$B$78,$A9,ヒアリング!$N$2:$N$78,"GAP") -> 0 | G9: =COUNTIFS(ヒアリング!$B$2:$B$78,$A9,ヒアリング!$N$2:$N$78,"対象外") -> 0 | H9: =C9-SUM(D9:G9) -> 2 | I9: =COUNTIFS(ヒアリング!$B$2:$B$78,$A9,ヒアリング!$N$2:$N$78,"GAP",ヒアリング!$R$2:$R$78,"ロジック改修") -> 0 | J9: =COUNTIFS(ヒアリング!$B$2:$B$78,$A9,ヒアリング!$Z$2:$Z$78,"決定済み") -> 0 | K9: =C9-J9 -> 2
A10: F-07 | B10: 実績管理（3層） | C10: =COUNTIF(ヒアリング!$B$2:$B$78,A10) -> 3 | D10: =COUNTIFS(ヒアリング!$B$2:$B$78,$A10,ヒアリング!$N$2:$N$78,"適合") -> 0 | E10: =COUNTIFS(ヒアリング!$B$2:$B$78,$A10,ヒアリング!$N$2:$N$78,"条件付き適合") -> 0 | F10: =COUNTIFS(ヒアリング!$B$2:$B$78,$A10,ヒアリング!$N$2:$N$78,"GAP") -> 0 | G10: =COUNTIFS(ヒアリング!$B$2:$B$78,$A10,ヒアリング!$N$2:$N$78,"対象外") -> 0 | H10: =C10-SUM(D10:G10) -> 3 | I10: =COUNTIFS(ヒアリング!$B$2:$B$78,$A10,ヒアリング!$N$2:$N$78,"GAP",ヒアリング!$R$2:$R$78,"ロジック改修") -> 0 | J10: =COUNTIFS(ヒアリング!$B$2:$B$78,$A10,ヒアリング!$Z$2:$Z$78,"決定済み") -> 0 | K10: =C10-J10 -> 3
A11: F-08 | B11: 小売売上計算 | C11: =COUNTIF(ヒアリング!$B$2:$B$78,A11) -> 3 | D11: =COUNTIFS(ヒアリング!$B$2:$B$78,$A11,ヒアリング!$N$2:$N$78,"適合") -> 0 | E11: =COUNTIFS(ヒアリング!$B$2:$B$78,$A11,ヒアリング!$N$2:$N$78,"条件付き適合") -> 0 | F11: =COUNTIFS(ヒアリング!$B$2:$B$78,$A11,ヒアリング!$N$2:$N$78,"GAP") -> 0 | G11: =COUNTIFS(ヒアリング!$B$2:$B$78,$A11,ヒアリング!$N$2:$N$78,"対象外") -> 0 | H11: =C11-SUM(D11:G11) -> 3 | I11: =COUNTIFS(ヒアリング!$B$2:$B$78,$A11,ヒアリング!$N$2:$N$78,"GAP",ヒアリング!$R$2:$R$78,"ロジック改修") -> 0 | J11: =COUNTIFS(ヒアリング!$B$2:$B$78,$A11,ヒアリング!$Z$2:$Z$78,"決定済み") -> 0 | K11: =C11-J11 -> 3
A12: F-09 | B12: 実量制契約電力判定 | C12: =COUNTIF(ヒアリング!$B$2:$B$78,A12) -> 2 | D12: =COUNTIFS(ヒアリング!$B$2:$B$78,$A12,ヒアリング!$N$2:$N$78,"適合") -> 0 | E12: =COUNTIFS(ヒアリング!$B$2:$B$78,$A12,ヒアリング!$N$2:$N$78,"条件付き適合") -> 0 | F12: =COUNTIFS(ヒアリング!$B$2:$B$78,$A12,ヒアリング!$N$2:$N$78,"GAP") -> 0 | G12: =COUNTIFS(ヒアリング!$B$2:$B$78,$A12,ヒアリング!$N$2:$N$78,"対象外") -> 0 | H12: =C12-SUM(D12:G12) -> 2 | I12: =COUNTIFS(ヒアリング!$B$2:$B$78,$A12,ヒアリング!$N$2:$N$78,"GAP",ヒアリング!$R$2:$R$78,"ロジック改修") -> 0 | J12: =COUNTIFS(ヒアリング!$B$2:$B$78,$A12,ヒアリング!$Z$2:$Z$78,"決定済み") -> 0 | K12: =C12-J12 -> 2
A13: F-10 | B13: 調達原価計算 | C13: =COUNTIF(ヒアリング!$B$2:$B$78,A13) -> 4 | D13: =COUNTIFS(ヒアリング!$B$2:$B$78,$A13,ヒアリング!$N$2:$N$78,"適合") -> 0 | E13: =COUNTIFS(ヒアリング!$B$2:$B$78,$A13,ヒアリング!$N$2:$N$78,"条件付き適合") -> 0 | F13: =COUNTIFS(ヒアリング!$B$2:$B$78,$A13,ヒアリング!$N$2:$N$78,"GAP") -> 0 | G13: =COUNTIFS(ヒアリング!$B$2:$B$78,$A13,ヒアリング!$N$2:$N$78,"対象外") -> 0 | H13: =C13-SUM(D13:G13) -> 4 | I13: =COUNTIFS(ヒアリング!$B$2:$B$78,$A13,ヒアリング!$N$2:$N$78,"GAP",ヒアリング!$R$2:$R$78,"ロジック改修") -> 0 | J13: =COUNTIFS(ヒアリング!$B$2:$B$78,$A13,ヒアリング!$Z$2:$Z$78,"決定済み") -> 0 | K13: =C13-J13 -> 4
A14: F-11 | B14: インバランス算定・BG按分 | C14: =COUNTIF(ヒアリング!$B$2:$B$78,A14) -> 3 | D14: =COUNTIFS(ヒアリング!$B$2:$B$78,$A14,ヒアリング!$N$2:$N$78,"適合") -> 0 | E14: =COUNTIFS(ヒアリング!$B$2:$B$78,$A14,ヒアリング!$N$2:$N$78,"条件付き適合") -> 0 | F14: =COUNTIFS(ヒアリング!$B$2:$B$78,$A14,ヒアリング!$N$2:$N$78,"GAP") -> 0 | G14: =COUNTIFS(ヒアリング!$B$2:$B$78,$A14,ヒアリング!$N$2:$N$78,"対象外") -> 0 | H14: =C14-SUM(D14:G14) -> 3 | I14: =COUNTIFS(ヒアリング!$B$2:$B$78,$A14,ヒアリング!$N$2:$N$78,"GAP",ヒアリング!$R$2:$R$78,"ロジック改修") -> 0 | J14: =COUNTIFS(ヒアリング!$B$2:$B$78,$A14,ヒアリング!$Z$2:$Z$78,"決定済み") -> 0 | K14: =C14-J14 -> 3
A15: F-12 | B15: 発電収支（FIP・発電側課金） | C15: =COUNTIF(ヒアリング!$B$2:$B$78,A15) -> 7 | D15: =COUNTIFS(ヒアリング!$B$2:$B$78,$A15,ヒアリング!$N$2:$N$78,"適合") -> 0 | E15: =COUNTIFS(ヒアリング!$B$2:$B$78,$A15,ヒアリング!$N$2:$N$78,"条件付き適合") -> 0 | F15: =COUNTIFS(ヒアリング!$B$2:$B$78,$A15,ヒアリング!$N$2:$N$78,"GAP") -> 0 | G15: =COUNTIFS(ヒアリング!$B$2:$B$78,$A15,ヒアリング!$N$2:$N$78,"対象外") -> 0 | H15: =C15-SUM(D15:G15) -> 7 | I15: =COUNTIFS(ヒアリング!$B$2:$B$78,$A15,ヒアリング!$N$2:$N$78,"GAP",ヒアリング!$R$2:$R$78,"ロジック改修") -> 0 | J15: =COUNTIFS(ヒアリング!$B$2:$B$78,$A15,ヒアリング!$Z$2:$Z$78,"決定済み") -> 0 | K15: =C15-J15 -> 7
... A30: N-06 | B30: 命名・開発規約 | C30: =COUNTIF(ヒアリング!$B$2:$B$78,A30) -> 1 | D30: =COUNTIFS(ヒアリング!$B$2:$B$78,$A30,ヒアリング!$N$2:$N$78,"適合") -> 0 | E30: =COUNTIFS(ヒアリング!$B$2:$B$78,$A30,ヒアリング!$N$2:$N$78,"条件付き適合") -> 0 | F30: =COUNTIFS(ヒアリング!$B$2:$B$78,$A30,ヒアリング!$N$2:$N$78,"GAP") -> 0 | G30: =COUNTIFS(ヒアリング!$B$2:$B$78,$A30,ヒアリング!$N$2:$N$78,"対象外") -> 0 | H30: =C30-SUM(D30:G30) -> 1 | I30: =COUNTIFS(ヒアリング!$B$2:$B$78,$A30,ヒアリング!$N$2:$N$78,"GAP",ヒアリング!$R$2:$R$78,"ロジック改修") -> 0 | J30: =COUNTIFS(ヒアリング!$B$2:$B$78,$A30,ヒアリング!$Z$2:$Z$78,"決定済み") -> 0 | K30: =C30-J30 -> 1
A31: 合計 | C31: =SUM(C4:C30) -> 77 | D31: =SUM(D4:D30) -> 0 | E31: =SUM(E4:E30) -> 0 | F31: =SUM(F4:F30) -> 0 | G31: =SUM(G4:G30) -> 0 | H31: =SUM(H4:H30) -> 77 | I31: =SUM(I4:I30) -> 0 | J31: =SUM(J4:J30) -> 0 | K31: =SUM(K4:K30) -> 77

Sheet 選択肢
A1: 判定 | B1: 対策区分 | C1: 影響度 | D1: 状態 | E1: 区分
A2: 適合 | B2: 設定 | C2: 大 | D2: 未着手 | E2: 機能確認
A3: 条件付き適合 | B3: マスタ追加 | C3: 中 | D3: 確認中 | E3: 制度確認
A4: GAP | B4: ロジック改修 | C4: 小 | D4: 回答済み | E4: 業務決定
A5: 対象外 | B5: 運用で回避 | D5: 決定済み | E5: 非機能
